jarvis_leaderboard/__init__.py
jarvis_leaderboard/jarvis_populate_data.py
jarvis_leaderboard/jarvis_serve.py
jarvis_leaderboard/jarvis_upload.py
jarvis_leaderboard/rebuild.py
jarvis_leaderboard/specialized_benchmarks.py
jarvis_leaderboard/update_metadata.py
jarvis_leaderboard/benchmarks/__init__.py
jarvis_leaderboard/benchmarks/benchmark_dois.json
jarvis_leaderboard/benchmarks/descriptions.csv
jarvis_leaderboard/benchmarks/AI/ImageClass/stem_2d_image_bravais_class.json.zip
jarvis_leaderboard/benchmarks/AI/SinglePropertyClass/dft_3d_magmom_oszicar.json.zip
jarvis_leaderboard/benchmarks/AI/SinglePropertyClass/dft_3d_mbj_bandgap.json.zip
jarvis_leaderboard/benchmarks/AI/SinglePropertyClass/dft_3d_n_powerfact.json.zip
jarvis_leaderboard/benchmarks/AI/SinglePropertyClass/dft_3d_optb88vdw_bandgap.json.zip
jarvis_leaderboard/benchmarks/AI/SinglePropertyClass/dft_3d_p_Seebeck.json.zip
jarvis_leaderboard/benchmarks/AI/SinglePropertyClass/dft_3d_slme.json.zip
jarvis_leaderboard/benchmarks/AI/SinglePropertyClass/dft_3d_spillage.json.zip
jarvis_leaderboard/benchmarks/AI/SinglePropertyPrediction/AGRA_CHO_ead.json.zip
jarvis_leaderboard/benchmarks/AI/SinglePropertyPrediction/AGRA_COOH_ead.json.zip
jarvis_leaderboard/benchmarks/AI/SinglePropertyPrediction/AGRA_CO_ead.json.zip
jarvis_leaderboard/benchmarks/AI/SinglePropertyPrediction/AGRA_OH_ead.json.zip
jarvis_leaderboard/benchmarks/AI/SinglePropertyPrediction/AGRA_O_ead.json.zip
jarvis_leaderboard/benchmarks/AI/SinglePropertyPrediction/dft_3d_Tc_supercon.json.zip
jarvis_leaderboard/benchmarks/AI/SinglePropertyPrediction/dft_3d_Tc_supercon_hydride.json.zip
jarvis_leaderboard/benchmarks/AI/SinglePropertyPrediction/dft_3d_Tc_supercon_hydride_plus_bulk.json.zip
jarvis_leaderboard/benchmarks/AI/SinglePropertyPrediction/dft_3d_avg_elec_mass.json.zip
jarvis_leaderboard/benchmarks/AI/SinglePropertyPrediction/dft_3d_avg_hole_mass.json.zip
jarvis_leaderboard/benchmarks/AI/SinglePropertyPrediction/dft_3d_bulk_modulus_kv.json.zip
jarvis_leaderboard-2024.10.30.dist-info/LICENSE.rst
jarvis_leaderboard-2024.10.30.dist-info/METADATA
jarvis_leaderboard-2024.10.30.dist-info/WHEEL
jarvis_leaderboard-2024.10.30.dist-info/top_level.txt
jarvis_leaderboard-2024.10.30.dist-info/RECORD
