Metadata-Version: 2.1
Name: jarvis_leaderboard
Version: 2024.10.30
Summary: jarvis_leaderboard
Home-page: https://github.com/knc6/jarvis_leaderboard
Author: Kamal Choudhary
Author-email: kamal.choudhary@nist.gov
Classifier: Programming Language :: Python :: 3
Classifier: License :: OSI Approved :: MIT License
Classifier: Operating System :: OS Independent
Requires-Python: >=3.8
License-File: LICENSE.rst
Requires-Dist: numpy>=1.19.5
Requires-Dist: scipy>=1.6.3
Requires-Dist: jarvis-tools>=2021.07.19
Requires-Dist: scikit-learn>=0.24.1
Requires-Dist: pandas>=1.2.4
Requires-Dist: rouge>=1.0.1
Requires-Dist: pydantic>=2.3.0
Requires-Dist: markdown>=3.2.1
Requires-Dist: plotly
Requires-Dist: absl-py==1.4.0
Requires-Dist: nltk==3.8.1
